beautified/__init__.py
beautified/style.py
beautified-1.0.0.dist-info/METADATA
beautified-1.0.0.dist-info/WHEEL
beautified-1.0.0.dist-info/top_level.txt
beautified-1.0.0.dist-info/RECORD
