Metadata-Version: 2.4
Name: beautified
Version: 1.0.0
Summary: A package for CLI text stylization.
Author: Chase Galloway
Author-email: chase.h.galloway21@gmail.com
Classifier: Programming Language :: Python :: 3
Classifier: Operating System :: OS Independent
Classifier: Topic :: Terminals
Requires-Python: >=3.6
Dynamic: author
Dynamic: author-email
Dynamic: classifier
Dynamic: requires-python
Dynamic: summary
